MANIFEST.in
README.md
requirements.txt
setup.py
test_requirements.txt
version.txt
./__init__.py
./chat.py
./competition_cli.py
./config.py
./constants.py
./feedback.py
./formatters.py
./http_client.py
./login_cli.py
./submit.py
./utils.py
./lib/__init__.py
./lib/binomial_tools.py
./lib/date_tools.py
./metrics/__init__.py
./metrics/baseline.py
./metrics/conversation_metrics.py
./metrics/feedback_metrics.py
./metrics/leaderboard_api.py
./metrics/leaderboard_cli.py
./metrics/leaderboard_formatter.py
./metrics/submission_metrics.py
./resources/bot_config/blade.json
./resources/bot_config/captain_wyatt.json
./resources/bot_config/coffee_shop_girl.json
./resources/bot_config/filbert.json
./resources/bot_config/leo.json
./resources/bot_config/levi.json
./resources/bot_config/mr_wilson.json
./resources/bot_config/nerd_girl.json
./resources/bot_config/scaramouche.json
./resources/bot_config/story_teller.json
./resources/bot_config/vampire_queen.json
./resources/bot_config/wednesday_addams.json
./schemas/__init__.py
./schemas/competition_schema.py
./schemas/date_range_schema.py
chaiverse_temp.egg-info/PKG-INFO
chaiverse_temp.egg-info/SOURCES.txt
chaiverse_temp.egg-info/dependency_links.txt
chaiverse_temp.egg-info/entry_points.txt
chaiverse_temp.egg-info/not-zip-safe
chaiverse_temp.egg-info/requires.txt
chaiverse_temp.egg-info/top_level.txt