Metadata-Version: 2.1
Name: chaiverse_temp
Version: 1.9.2
Summary: Chaiverse
Home-page: https://www.chaiverse.com
Author: Chai Research Corp.
Author-email: hello@chai-research.com
License: MIT
Requires-Dist: click
Requires-Dist: dateparser
Requires-Dist: numpy
Requires-Dist: pandas
Requires-Dist: pydantic==1.10.14
Requires-Dist: requests
Requires-Dist: tqdm
Requires-Dist: tabulate
